paddlelibrosa/__init__.py
paddlelibrosa/augmentation.py
paddlelibrosa/stft.py
paddlelibrosa/paddleplus/__init__.py
paddlelibrosa-0.0.1.dist-info/LICENSE
paddlelibrosa-0.0.1.dist-info/METADATA
paddlelibrosa-0.0.1.dist-info/WHEEL
paddlelibrosa-0.0.1.dist-info/top_level.txt
paddlelibrosa-0.0.1.dist-info/RECORD
