Metadata-Version: 2.1
Name: paddlelibrosa
Version: 0.0.1
Summary: Paddle implemention of part of librosa functions.
Home-page: https://github.com/agentmaker/paddlelibrosa
License: UNKNOWN
Platform: UNKNOWN
Classifier: Programming Language :: Python :: 3
Classifier: License :: OSI Approved :: MIT License
Classifier: Operating System :: OS Independent
Requires-Python: >=3.6
Requires-Dist: numpy
Requires-Dist: librosa (>=0.7.0)
